main.py
src/__init__.py
src/embeddings.py
src/models.py
src/security.py
src/task_store.py
vector_task_mcp-1.2.16.dist-info/licenses/LICENSE
vector_task_mcp-1.2.16.dist-info/METADATA
vector_task_mcp-1.2.16.dist-info/WHEEL
vector_task_mcp-1.2.16.dist-info/entry_points.txt
vector_task_mcp-1.2.16.dist-info/top_level.txt
vector_task_mcp-1.2.16.dist-info/RECORD
