Metadata-Version: 2.4
Name: vector-task-mcp
Version: 1.2.16
Summary: A secure, vector-based task management server for Claude Desktop using sqlite-vec and sentence-transformers
Author-email: Xsaven <xsaven@gmail.com>
License-Expression: MIT
Project-URL: Homepage, https://github.com/xsaven/vector-task-mcp
Project-URL: Repository, https://github.com/xsaven/vector-task-mcp
Project-URL: Issues, https://github.com/xsaven/vector-task-mcp/issues
Keywords: mcp,model-context-protocol,task-management,sqlite,embeddings,semantic-search,claude,ai-tasks
Classifier: Development Status :: 4 - Beta
Classifier: Intended Audience :: Developers
Classifier: Programming Language :: Python :: 3
Classifier: Programming Language :: Python :: 3.10
Classifier: Programming Language :: Python :: 3.11
Classifier: Programming Language :: Python :: 3.12
Classifier: Topic :: Software Development :: Libraries :: Python Modules
Classifier: Topic :: Scientific/Engineering :: Artificial Intelligence
Requires-Python: >=3.10
License-File: LICENSE
Requires-Dist: mcp>=0.3.0
Requires-Dist: sqlite-vec>=0.1.6
Requires-Dist: sentence-transformers>=2.2.2
Dynamic: license-file
